antibodies/__init__.py
antibodies/detect.py
llm_antibodies-0.0.1.dist-info/LICENSE
llm_antibodies-0.0.1.dist-info/METADATA
llm_antibodies-0.0.1.dist-info/WHEEL
llm_antibodies-0.0.1.dist-info/top_level.txt
llm_antibodies-0.0.1.dist-info/RECORD
