Metadata-Version: 2.1
Name: llm-antibodies
Version: 0.0.1
Summary: Antibodies for LLM hallucinations
Home-page: https://github.com/rafaelsandroni/antibodies
Author: rafaelsandroni
Author-email: Rafael Sandroni <rafael@metatext.io>
Project-URL: Homepage, https://github.com/rafaelsandroni/antibodies
Project-URL: Issues, https://github.com/rafaelsandroni/antibodies/issues
Classifier: Programming Language :: Python :: 3
Classifier: License :: OSI Approved :: MIT License
Classifier: Operating System :: OS Independent
Requires-Python: >=3.8
License-File: LICENSE
